{
    "Abhivyakti_Sponsors_2025": {
        "Title Sponsor": [
            {
                "images": [
                    {
                        "img": "/assets/HomePage/Sponsors/SponsorPic/current/amul.png",
                        "name": "Amul",
                        "link": "https://amul.com/"
                    }
                ]
            }
        ],
        "Co-Sponsor": [
            {
                "images": [
                    {
                        "img": "/assets/HomePage/Sponsors/SponsorPic/current/sbi.jpg",
                        "name": "SBI",
                        "link": "https://www.onlinesbi.sbi/"
                    }
                ]
            }
        ],
        "Powered By": [
            {
                "images": [
                    {
                        "img": "/assets/HomePage/Sponsors/SponsorPic/current/canara.png",
                        "name": "Canara Bank",
                        "link": "https://canarabank.com/"
                    }
                ]
            }
        ],
        "Associate Sponsors": [
            {
                "images": [
                    {
                        "img": "/assets/HomePage/Sponsors/SponsorPic/current/bxi.png",
                        "name": "BXI",
                        "link": "https://bxiworld.com/"
                    },
                    {
                        "img": "/assets/HomePage/Sponsors/SponsorPic/current/vlcc.JPG",
                        "name": "VLCC",
                        "link": "https://vlcc.com/"
                    }
                ]
            }
        ],
        "Radio Partner": [
            {
                "images": [
                    {
                        "img": "/assets/HomePage/Sponsors/SponsorPic/current/radio.jpg",
                        "name": "Radio City",
                        "link": ""
                    }
                ]
            }
        ],
        "Athleisure Partner": [
            {
                "images": [
                    {
                        "img": "/assets/HomePage/Sponsors/SponsorPic/current/skechers.png",
                        "name": "Skechers",
                        "link": "https://www.skechers.in/"
                    }
                ]
            }
        ],
        "Smartphone Partner": [
            {
                "images": [
                    {
                        "img": "/assets/HomePage/Sponsors/SponsorPic/current/vivo.png",
                        "name": "Vivo",
                        "link": "https://www.vivo.com/in"
                    }
                ]
            }
        ],
        "E-Sports Partner": [
            {
                "images": [
                    {
                        "img": "/assets/HomePage/Sponsors/SponsorPic/current/krafton.png",
                        "name": "Krafton Gaming",
                        "link": "https://krafton.com/en/"
                    }
                ]
            }
        ],
        "Snacking Partner": [
            {
                "images": [
                    {
                        "img": "/assets/HomePage/Sponsors/SponsorPic/current/diamond.png",
                        "name": "Diamond Chips",
                        "link": "https://www.yellowdiamond.in/products/chips/"
                    }
                ]
            }
        ],
        "Self-Care Partner": [
            {
                "images": [
                    {
                        "img": "/assets/HomePage/Sponsors/SponsorPic/current/collegebrand.jpg",
                        "name": "College Brand Connect",
                        "link": ""
                    },
                    {
                        "img": "/assets/HomePage/Sponsors/SponsorPic/current/smart.png",
                        "name": "Smart and Handsome",
                        "link": ""
                    }
                ]
            }
        ],
        "Real Estate Partner": [
            {
                "images": [
                    {
                        "img": "/assets/HomePage/Sponsors/SponsorPic/current/green.jpg",
                        "name": "SSD GReen Future",
                        "link": ""
                    }
                ]
            }
        ],
        "Media Partner": [
            {
                "images": [
                    {
                        "img": "/assets/HomePage/Sponsors/SponsorPic/current/timesofindia.png",
                        "name": "Times Of India",
                        "link": "https://timesofindia.indiatimes.com/"
                    }
                ]
            }
        ],
        "Audio Partner": [
            {
                "images": [
                    {
                        "img": "/assets/HomePage/Sponsors/SponsorPic/current/zebronics.png",
                        "name": "Zebronics",
                        "link": "https://zebronics.com/"
                    }
                ]
            }
        ],
        "Gifting Partner": [
            {
                "images": [
                    {
                        "img": "/assets/HomePage/Sponsors/SponsorPic/current/tokristory.jpg",
                        "name": "Tokri Story",
                        "link": ""
                    }
                ]
            }
        ],
        "Fandom Partner": [
            {
                "images": [
                    {
                        "img": "/assets/HomePage/Sponsors/SponsorPic/current/escapedoor.png",
                        "name": "The Escape Door",
                        "link": ""
                    }
                ]
            }
        ],
        "Travel Partner": [
            {
                "images": [
                    {
                        "img": "/assets/HomePage/Sponsors/SponsorPic/current/easemytrip.jpg",
                        "name": "EaseMyTrip",
                        "link": "https://www.easemytrip.com/"
                    }
                ]
            }
        ],
        "Bus Travel Partner": [
            {
                "images": [
                    {
                        "img": "/assets/HomePage/Sponsors/SponsorPic/current/abhibus.png",
                        "name": "AbhiBus",
                        "link": "https://www.abhibus.com/"
                    }
                ]
            }
        ],
        "Coffee Partner": [
            {
                "images": [
                    {
                        "img": "/assets/HomePage/Sponsors/SponsorPic/current/xoldbrews.jpg",
                        "name": "Xoldbrews",
                        "link": "https://xoldbrews.com/"
                    }
                ]
            }
        ],
        "Jewellery Partner": [
            {
                "images": [
                    {
                        "img": "/assets/HomePage/Sponsors/SponsorPic/current/tanishq.png",
                        "name": "Mia by Tanishq",
                        "link": "https://www.miabytanishq.com/en_IN/wedding-gifting?utm_source=Google&utm_medium=CPC&utm_campaign=HM_Google_Perf_Search_Brand&gad_source=1&gclid=CjwKCAiAzvC9BhADEiwAEhtlN75ddDfZ9HhIVauKEUrLRUe28JfTbPj01stUaCl5w-c-nxrsPTGdpBoCQN0QAvD_BwE"
                    }
                ]
            }
        ],
        "Energy Drink Partner": [
            {
                "images": [
                    {
                        "img": "/assets/HomePage/Sponsors/SponsorPic/current/hell.png",
                        "name": "Hell Energy",
                        "link": "https://www.hellenergy.com/in/"
                    }
                ]
            }
        ],
        "Community Partners": [
            {
                "images": [
                    {
                        "img": "/assets/HomePage/Sponsors/SponsorPic/current/iiitnian.png",
                        "name": "IIITians Network",
                        "link": "https://github.com/IIITians-Network"
                    },
                    {
                        "img": "/assets/HomePage/Sponsors/SponsorPic/current/iitnit.jpg",
                        "name": "IIT NIT IIIT",
                        "link": ""
                    }
                ]
            }
        ],
        "Financial Literacy Partner": [
            {
                "images": [
                    {
                        "img": "/assets/HomePage/Sponsors/SponsorPic/current/stockedge.png",
                        "name": "StockEdge",
                        "link": "https://stockedge.com/?srsltid=AfmBOopd8msMf6utdJpGeXxjZAfLHs7MhSxZsWzjLhSnwrMEqRWXo-Lp"
                    }
                ]
            }
        ],
        "Blog Partner": [
            {
                "images": [
                    {
                        "img": "/assets/HomePage/Sponsors/SponsorPic/current/edtimes.png",
                        "name": "ED Times",
                        "link": "https://edtimes.in/"
                    }
                ]
            }
        ],
        "Beverage Partner": [
            {
                "images": [
                    {
                        "img": "/assets/HomePage/Sponsors/SponsorPic/current/urban.png",
                        "name": "Urban Monk",
                        "link": ""
                    }
                ]
            }
        ],
        "Oral-Care Partner": [
            {
                "images": [
                    {
                        "img": "/assets/HomePage/Sponsors/SponsorPic/current/qelica.png",
                        "name": "Qelica",
                        "link": "https://qelicacare.com/"
                    }
                ]
            }
        ],
        "AB Central Sponsors": [
            {
                "images": [
                    {
                        "img": "/assets/HomePage/Sponsors/SponsorPic/current/qelica.png",
                        "name": "Qelica",
                        "link": "https://qelicacare.com/"
                    },
                    {
                        "img": "/assets/HomePage/Sponsors/SponsorPic/current/unstop.png",
                        "name": "Unstop",
                        "link": "https://unstop.com/"
                    },
                    {
                        "img": "/assets/HomePage/Sponsors/SponsorPic/current/anusaya.png",
                        "name": "Anusaya Beauty World",
                        "link": ""
                    },
                    {
                        "img": "/assets/HomePage/Sponsors/SponsorPic/current/paridhan.jpg",
                        "name": "Paridhan",
                        "link": ""
                    }
                ]
            }
        ],
        "Crescendo Sponsors": [
            {
                "images": [
                    {
                        "img": "/assets/HomePage/Sponsors/SponsorPic/current/lawrence.png",
                        "name": "Lawrence & Mayo Opticals",
                        "link": "https://lawrenceandmayo.com/"
                    },
                    {
                        "img": "/assets/HomePage/Sponsors/SponsorPic/current/reset.png",
                        "name": "Arogya Quest Wellness ",
                        "link": ""
                    },
                    {
                        "img": "/assets/HomePage/Sponsors/SponsorPic/current/rowdy.jpg",
                        "name": "Rowdy Momos",
                        "link": "https://rowdymomos.com/"
                    }
                ]
            }
        ],
        "D-Taraxia Sponsors": [
            {
                "images": [
                    {
                        "img": "/assets/HomePage/Sponsors/SponsorPic/current/examprep.jpg",
                        "name": "Exam Prep Tool",
                        "link": "https://exampreptool.com/"
                    },
                    {
                        "img": "/assets/HomePage/Sponsors/SponsorPic/current/student.png",
                        "name": "Student Tribe",
                        "link": "https://www.studenttribe.in/"
                    }
                ]
            }
        ],
        "Estoria Sponsors": [
            {
                "images": [
                    {
                        "img": "/assets/HomePage/Sponsors/SponsorPic/current/truscholar.png",
                        "name": "TruScholar",
                        "link": "https://www.truscholar.io/"
                    },
                    {
                        "img": "/assets/HomePage/Sponsors/SponsorPic/current/agromania.png",
                        "name": "Agromania",
                        "link": "https://agromania.in/"
                    },
                    {
                        "img": "/assets/HomePage/Sponsors/SponsorPic/current/sheela.png",
                        "name": "Sheela Ad Makers",
                        "link": "https://www.sheelaadmaker.com/"
                    },
                    {
                        "img": "/assets/HomePage/Sponsors/SponsorPic/current/teztecch.jpg",
                        "name": "TezTecch",
                        "link": "https://teztecch.com/"
                    }
                ]
            }
        ],
        "Orator Sponsors": [
            {
                "images": [
                    {
                        "img": "/assets/HomePage/Sponsors/SponsorPic/current/storify.jpg",
                        "name": "Storify News",
                        "link": "https://www.storifynews.com/"
                    },
                    {
                        "img": "/assets/HomePage/Sponsors/SponsorPic/current/timesofindia.png",
                        "name": "Times Of India",
                        "link": "https://timesofindia.indiatimes.com/"
                    }
                ]
            }
        ],
        "Strokes Sponsors": [
            {
                "images": [
                    {
                        "img": "/assets/HomePage/Sponsors/SponsorPic/current/ideas.jpg",
                        "name": "Ideas",
                        "link": "https://ideasnagpur.edu.in/"
                    }
                ]
            }
        ]
    }
}